nt-crawler/__init__.py
nt-crawler/src/__init__.py
nt-crawler/src/nt.py
nt-crawler/src/service/__init__.py
nt-crawler/src/service/nt.py
nt_crawler/__init__.py
nt_crawler/src/__init__.py
nt_crawler/src/nt.py
nt_crawler/src/service/__init__.py
nt_crawler/src/service/nt.py
nt_test-0.0.2.dist-info/METADATA
nt_test-0.0.2.dist-info/WHEEL
nt_test-0.0.2.dist-info/entry_points.txt
nt_test-0.0.2.dist-info/top_level.txt
nt_test-0.0.2.dist-info/RECORD
