Metadata-Version: 2.1
Name: nt-test
Version: 0.0.2
Summary: newstower
Home-page: https://github.com/pypa/sampleproject
Author: newstower
Author-email: kj2945@gmail.com
License: UNKNOWN
Platform: UNKNOWN
Classifier: Programming Language :: Python :: 3
Classifier: Operating System :: OS Independent
Requires-Python: >=3.6
